mcp_simple_pubmed/__init__.py
mcp_simple_pubmed/__main__.py
mcp_simple_pubmed/fulltext_client.py
mcp_simple_pubmed/pubmed_client.py
mcp_simple_pubmed/pubmed_fetch.py
mcp_simple_pubmed/pubmed_search.py
mcp_simple_pubmed/server.py
mcp_simple_pubmed-0.1.14.dist-info/licenses/LICENSE
mcp_simple_pubmed-0.1.14.dist-info/METADATA
mcp_simple_pubmed-0.1.14.dist-info/WHEEL
mcp_simple_pubmed-0.1.14.dist-info/entry_points.txt
mcp_simple_pubmed-0.1.14.dist-info/top_level.txt
mcp_simple_pubmed-0.1.14.dist-info/RECORD
